setup.cfg
setup.py
Agora_Service_Provider.egg-info/PKG-INFO
Agora_Service_Provider.egg-info/SOURCES.txt
Agora_Service_Provider.egg-info/dependency_links.txt
Agora_Service_Provider.egg-info/namespace_packages.txt
Agora_Service_Provider.egg-info/requires.txt
Agora_Service_Provider.egg-info/top_level.txt
agora/__init__.py
agora/provider/__init__.py
agora/provider/jobs/__init__.py
agora/provider/jobs/collect.py
agora/provider/server/__init__.py
agora/provider/server/base.py