Metadata-Version: 1.1
Name: Agora-Service-Provider
Version: 0.0.16
Summary: A library for making web services built on the Agora
Home-page: https://github.com/smartdeveloperhub/agora-service-provider
Author: Fernando Serena
Author-email: fernando.serena@centeropenmiddleware.com
License: Apache 2
Download-URL: https://github.com/smartdeveloperhub/agora-service-provider/tarball/0.0.1
Keywords: linked-data,path,ontology,plan
Platform: UNKNOWN
